[
    {
        "month": 5,
        "page": 2,
        "thead": [
            "카테고리",
            "기간",
            "",
            "내용"
        ],
        "tbody": [
            {
                "td_texts": [
                    "학사일정",
                    "2024.05.14 ~ 2024.05.17"
                ],
                "td_a_texts": [
                    "하계 계절수업 예비수강신청"
                ],
                "td_p_texts": [
                    "학사지원과"
                ]
            },
            {
                "td_texts": [
                    "모집",
                    "2024.05.02 ~ 2024.05.17"
                ],
                "td_a_texts": [
                    "채용연계 풀스택과정(JAVA) 교육생 모집"
                ],
                "td_p_texts": [
                    "취창업지원과"
                ]
            },
            {
                "td_texts": [
                    "행사·회의",
                    "2024.05.18"
                ],
                "td_a_texts": [
                    "익산시민과 함께하는 열린음악회[원광새마을금고 창립 45주년 기념]"
                ],
                "td_p_texts": [
                    "대외협력홍보과"
                ]
            },
            {
                "td_texts": [
                    "교육·특강",
                    "2024.05.23"
                ],
                "td_a_texts": [
                    "충주맨 김선태 주무관[비교과통합센터 오감만족 홀림 특강]"
                ],
                "td_p_texts": [
                    "관리자"
                ]
            },
            {
                "td_texts": [
                    "행사·회의",
                    "2024.05.28"
                ],
                "td_a_texts": [
                    "한국의 홍보 전문가가 들려주는 동북아 평화 이야기-한국 문화와 역사 홍보, 왜 중요한가[2024학년도 55차 NEAD 콜로키움/동북아시아인문사회연구소]"
                ],
                "td_p_texts": [
                    "대외협력홍보과"
                ]
            },
            {
                "td_texts": [
                    "etc",
                    "2024.05.28 ~ 2024.05.29"
                ],
                "td_a_texts": [
                    "하계 계절수업 본수강신청"
                ],
                "td_p_texts": [
                    "학사지원과"
                ]
            },
            {
                "td_texts": [
                    "학사일정",
                    "2024.05.28 ~ 2024.05.29"
                ],
                "td_a_texts": [
                    "하계 계절수업 본수강신청"
                ],
                "td_p_texts": [
                    "학사지원과"
                ]
            },
            {
                "td_texts": [
                    "모집",
                    "2024.05.27 ~ 2024.06.13"
                ],
                "td_a_texts": [
                    "학생역량개발센터 연구교수 초빙 공고[원광대학교]"
                ],
                "td_p_texts": [
                    "관리자"
                ]
            },
            {
                "td_texts": [
                    "학사·장학",
                    "2024.05.21 ~ 2024.06.20"
                ],
                "td_a_texts": [
                    "2024년 2학기 국가장학금(1차) 신청 안내"
                ],
                "td_p_texts": [
                    "장학복지과"
                ]
            },
            {
                "td_texts": [
                    "공모",
                    "2024.05.13 ~ 2024.06.28"
                ],
                "td_a_texts": [
                    "(공모전) 2024 학교급식 캐릭터 공모전 안내[교육부]"
                ],
                "td_p_texts": [
                    "관리자"
                ]
            }
        ]
    }
]